myrcella/__init__.py
myrcella/control.py
myrcella/database.py
myrcella/main.py
myrcella/report.py
myrcella/server.py
myrcella/data_files/endpoints/example.yml
myrcella/data_files/settings/default.ini
myrcella-0.2.3.dist-info/LICENSE
myrcella-0.2.3.dist-info/METADATA
myrcella-0.2.3.dist-info/WHEEL
myrcella-0.2.3.dist-info/entry_points.txt
myrcella-0.2.3.dist-info/top_level.txt
myrcella-0.2.3.dist-info/RECORD
