Metadata-Version: 2.1
Name: myrcella
Version: 0.2.3
Summary: Simple API server to collect data according to dynamically loaded yaml specifications
Home-page: https://github.com/krateng/myrcella
Author: Johannes Krattenmacher
Author-email: python@krateng.dev
License: GPLv3
Platform: UNKNOWN
Classifier: Programming Language :: Python :: 3
Classifier: License :: OSI Approved :: GNU General Public License v3 (GPLv3)
Classifier: Operating System :: OS Independent
Requires-Python: >=3.5
Requires-Dist: bottle (>=0.12.16)
Requires-Dist: waitress (>=1.3)
Requires-Dist: doreah (>=1.4)
